cdnbestip/__init__.py
cdnbestip/cli.py
cdnbestip/config.py
cdnbestip/dns.py
cdnbestip/exceptions.py
cdnbestip/ip_sources.py
cdnbestip/logging_config.py
cdnbestip/models.py
cdnbestip/results.py
cdnbestip/speedtest.py
cdnbestip-0.1.0.dist-info/licenses/LICENSE
cdnbestip-0.1.0.dist-info/METADATA
cdnbestip-0.1.0.dist-info/WHEEL
cdnbestip-0.1.0.dist-info/entry_points.txt
cdnbestip-0.1.0.dist-info/top_level.txt
cdnbestip-0.1.0.dist-info/RECORD
