Metadata-Version: 2.4
Name: cdnbestip
Version: 0.1.0
Summary: CDN speed testing and management tool
Author: Jetsung Chan <i@jetsung.com>
Maintainer: Jetsung Chan <i@jetsung.com>
License-Expression: Apache-2.0
Project-URL: Homepage, https://github.com/idev-sig/cdnbestip
Project-URL: Documentation, https://github.com/idev-sig/cdnbestip#readme
Project-URL: Repository, https://github.com/idev-sig/cdnbestip.git
Project-URL: Issues, https://github.com/idev-sig/cdnbestip/issues
Project-URL: Changelog, https://github.com/idev-sig/cdnbestip/releases
Keywords: cloudflare,dns,speed-test,cdn,optimization,networking
Classifier: Development Status :: 5 - Production/Stable
Classifier: Environment :: Console
Classifier: Intended Audience :: Developers
Classifier: Intended Audience :: System Administrators
Classifier: Operating System :: OS Independent
Classifier: Programming Language :: Python :: 3
Classifier: Programming Language :: Python :: 3.13
Classifier: Programming Language :: Python :: 3.14
Classifier: Topic :: Internet :: Name Service (DNS)
Classifier: Topic :: System :: Networking
Classifier: Topic :: System :: Systems Administration
Classifier: Topic :: Utilities
Requires-Python: >=3.13
License-File: LICENSE
Requires-Dist: cloudflare>=4.3.1
Requires-Dist: requests>=2.31.0
Provides-Extra: dev
Requires-Dist: pytest>=8.4.2; extra == "dev"
Requires-Dist: pytest-cov>=4.0.0; extra == "dev"
Requires-Dist: pytest-mock>=3.12.0; extra == "dev"
Requires-Dist: black>=23.0.0; extra == "dev"
Requires-Dist: ruff>=0.1.0; extra == "dev"
Requires-Dist: pre-commit>=3.6.0; extra == "dev"
Provides-Extra: test
Requires-Dist: pytest>=8.4.2; extra == "test"
Requires-Dist: pytest-cov>=4.0.0; extra == "test"
Requires-Dist: pytest-mock>=3.12.0; extra == "test"
Requires-Dist: responses>=0.24.0; extra == "test"
Dynamic: license-file
